wecom_sdk/__init__.py
wecom_sdk/etc/constants.py
wecom_sdk/exceptions/general.py
wecom_sdk/modules/base.py
wecom_sdk/modules/department.py
wecom_sdk/modules/message.py
wecom_sdk/modules/mixin.py
wecom_sdk/modules/users.py
wecom_sdk/schemas/base.py
wecom_sdk/schemas/departments.py
wecom_sdk/schemas/message.py
wecom_sdk/schemas/token.py
wecom_sdk/schemas/users.py
wecom_sdk/utils/convert.py
wecom_sdk/utils/requests.py
wecom_sdk-1.0.0.dist-info/LICENSE
wecom_sdk-1.0.0.dist-info/METADATA
wecom_sdk-1.0.0.dist-info/WHEEL
wecom_sdk-1.0.0.dist-info/RECORD
